{
    "exp0": {
        "training": [
            "0",
            "1",
            "2"
        ],
        "validation": [
            "3"
        ],
        "test": [
            "4"
        ]
    },
    "exp1": {
        "training": [
            "1",
            "2",
            "3"
        ],
        "validation": [
            "4"
        ],
        "test": [
            "0"
        ]
    },
    "exp2": {
        "training": [
            "2",
            "3",
            "4"
        ],
        "validation": [
            "0"
        ],
        "test": [
            "1"
        ]
    },
    "exp3": {
        "training": [
            "3",
            "4",
            "0"
        ],
        "validation": [
            "1"
        ],
        "test": [
            "2"
        ]
    },
    "exp4": {
        "training": [
            "4",
            "0",
            "1"
        ],
        "validation": [
            "2"
        ],
        "test": [
            "3"
        ]
    }
}